{
  "_id": "p8",
  "name": "Прихожая 2",
  "title": "Прихожая 2",
  "h3name": "Готовый проект прихожей, габарит - 2175(В)х950(Ш)х370(Г).",
  "describtion": "Готовый проект прихожей, габарит - 2175(В)х950(Ш)х370(Г).",
  "img": "p2.jpg",
  "imgArr": ["p2.jpg"],
  "anons": "Готовый проект прихожей, габарит - 2175(В)х950(Ш)х370(Г).",
  "content": "Готовый проект прихожей, габарит - 2175(В)х950(Ш)х370(Г).",
  "gabarit": { "h": 2175, "w": 950, "l": 370 },
  "dgNumber": "1465720",
  "visible": true,
  "hits": false,
  "new": true,
  "sale": true,
  "price": 100,
  "date": "2016-02-20",
  "fileSize": "486Kb",
  "filePages": 25,
  "optraskroy": "",
  "free": false
}
